simple_markdown_crawler/__init__.py
simple_markdown_crawler/cli.py
simple_markdown_crawler-0.2.0.dist-info/licenses/LICENSE.txt
simple_markdown_crawler-0.2.0.dist-info/METADATA
simple_markdown_crawler-0.2.0.dist-info/WHEEL
simple_markdown_crawler-0.2.0.dist-info/entry_points.txt
simple_markdown_crawler-0.2.0.dist-info/top_level.txt
simple_markdown_crawler-0.2.0.dist-info/RECORD
