Metadata-Version: 2.4
Name: simple-markdown-crawler
Version: 0.2.0
Summary: A multithreaded 🕸️ web crawler that recursively crawls a website and creates a 🔽 markdown file for each page
Author-email: Jose Maldonado <josemald89@gmail.com>
License-Expression: MIT
Project-URL: Homepage, https://github.com/yukiteruamano/simple-markdown-crawler
Project-URL: Bug Tracker, https://github.com/yukiteruamano/simple-markdown-crawler/issues
Project-URL: Twitter, https://x.com/Yukiteru_Amano
Classifier: Programming Language :: Python :: 3
Classifier: Operating System :: OS Independent
Requires-Python: >=3.10
License-File: LICENSE.txt
Requires-Dist: beautifulsoup4>=4.13.0
Requires-Dist: markdownify>=1.1.0
Requires-Dist: requests>=2.32.0
Dynamic: license-file
